ahservo
