Metadata-Version: 1.0
Name: ahservo
Version: 1.1.0
Summary: Control servo with an angle between 0 and 180 degrees
Home-page: UNKNOWN
Author: sashankMNS
Author-email: UNKNOWN
License: MIT
Platform: UNKNOWN
